_virtualenv_asdf/__init__.py
_virtualenv_asdf/discovery.py
virtualenv_asdf-0.1.0.dist-info/entry_points.txt
virtualenv_asdf-0.1.0.dist-info/LICENSE
virtualenv_asdf-0.1.0.dist-info/WHEEL
virtualenv_asdf-0.1.0.dist-info/METADATA
virtualenv_asdf-0.1.0.dist-info/RECORD
